donutlib.py
setup.py
DonutLib.egg-info/PKG-INFO
DonutLib.egg-info/SOURCES.txt
DonutLib.egg-info/dependency_links.txt
DonutLib.egg-info/top_level.txt